gtn_tools/__init__.py
gtn_tools/exceptions/__init__.py
gtn_tools/exceptions/quote_exceptions.py
gtn_tools/exceptions/speech_exceptions.py
gtn_tools/exceptions/translation_exceptions.py
gtn_tools/quote/Doc.py
gtn_tools/quote/Quote.py
gtn_tools/quote/__init__.py
gtn_tools/quote/helpers.py
gtn_tools-1.8.0.dist-info/LICENSE
gtn_tools-1.8.0.dist-info/WHEEL
gtn_tools-1.8.0.dist-info/METADATA
gtn_tools-1.8.0.dist-info/RECORD
