Metadata-Version: 2.1
Name: gtn-tools
Version: 1.8.0
Summary: Common tools and utils for GeTraNet APIs and internal services.
Author: GeTraNet
Author-email: dev@getranet.de
Requires-Python: >=3.8,<3.11
Classifier: Programming Language :: Python :: 3
Classifier: Programming Language :: Python :: 3.10
Classifier: Programming Language :: Python :: 3.8
Classifier: Programming Language :: Python :: 3.9
Requires-Dist: Pillow (>=8.3.2,<9.0.0)
Requires-Dist: ShopifyAPI (>=10.0.0,<11.0.0)
Requires-Dist: XlsxWriter (>=3.0.1,<4.0.0)
Requires-Dist: attrs (>=21.2.0,<22.0.0)
Requires-Dist: google-cloud-speech (>=2.10.0,<3.0.0)
Requires-Dist: google-cloud-storage (>=1.42.3,<2.0.0)
Requires-Dist: google-cloud-translate (>=3.5.0,<4.0.0)
Requires-Dist: imutils (>=0.5.4,<0.6.0)
Requires-Dist: iniconfig (>=1.1.1,<2.0.0)
Requires-Dist: langdetect (>=1.0.9,<2.0.0)
Requires-Dist: lxml (>=4.6.3,<5.0.0)
Requires-Dist: numpy (>=1.21.2,<2.0.0)
Requires-Dist: opencv-python (>=4.5.3,<5.0.0)
Requires-Dist: pdf2image (>=1.16.0,<2.0.0)
Requires-Dist: pluggy (>=1.0.0,<2.0.0)
Requires-Dist: py (>=1.10.0,<2.0.0)
Requires-Dist: pydantic (>=1.8.2,<2.0.0)
Requires-Dist: pydub (>=0.25.1,<0.26.0)
Requires-Dist: pyparsing (>=2.4.7,<3.0.0)
Requires-Dist: python-docx (>=0.8.11,<0.9.0)
Requires-Dist: python-pptx (>=0.6.21,<0.7.0)
Requires-Dist: six (>=1.16.0,<2.0.0)
Requires-Dist: srt (>=3.5.0,<4.0.0)
Requires-Dist: starlette (>=0.16.0,<0.17.0)
Requires-Dist: tesserocr (>=2.5.2,<3.0.0)
Requires-Dist: toml (>=0.10.2,<0.11.0)
